Workbook

Sheet Read Me
A1: OIL DISTRIBUTION — COSTING & PRICING WORKBOOK
A2: A formula-driven workbook to cost products, set retail & wholesale prices, compare suppliers, and test pricing scenarios. No macros or VBA are used.
A4: COLOR CODE — WHAT EACH CELL COLOR MEANS
A5: INPUT | B5: Blue text on pale yellow. Type your own numbers/text here. Safe to edit.
A6: FORMULA | B6: Black text, white background. Calculated automatically — do not overwrite. Sheets are protected so these are locked.
A7: KEY OUTPUT | B7: Bold green text on pale green. The main answer/result of a section.
A9: WHAT EACH WORKSHEET DOES
A10: Business Settings | B10: Business-wide assumptions (markups, margins, VAT, currency, freight allocation, quantity-discount tiers). Edit here and the values flow automatically into every other sheet.
A11: Product Costing | B11: Your product database. One row per product/purchase: supplier, purchase cost, quantity, and up to 8 renameable expenses. Automatically computes Total Expenses, Total Landed Cost, and Cost per Unit.
A12: Pricing Calculator | B12: Three quick calculators: (1) Cost -> Selling Price, (2) Selling Price -> Maximum Purchase Cost, (3) Target Profit -> Selling Price.
A13: Retail & Wholesale Pricing | B13: Enter a product's cost once and see Retail price, Wholesale price, and 5 quantity-discount tiers, all updating together.
A14: Supplier Comparison | B14: Compare up to 4 suppliers for the same product side by side. Lowest cost and highest profit are highlighted automatically.
A15: Profit Simulator | B15: A free-form 'what if' scenario sheet — change any cost, expense or markup and instantly see the new price, profit and margin.
A16: Sensitivity Analysis | B16: Shows what happens to profit if purchase cost, expenses, or selling price move up or down.
A17: Dashboard | B17: Pick a product from the dropdown and see all its key numbers (KPIs) and two simple charts in one place.
A18: Break-even Calculator | B18: The minimum selling price where you don't lose money, plus your safety cushion at your current price.
A19: Price Negotiation Tool | B19: See exactly how a new supplier quote changes your cost, profit, and the selling price you'd need to hold your margin.
A20: Reverse Cost Calculator | B20: Working backward from a customer's budget and your desired profit, finds the maximum you can afford to pay a supplier.
A21: Product Profitability Summary | B21: All products ranked automatically from most to least profitable (retail).
A22: Inventory Planning | B22: Simple beginning/purchases/sold tracker with ending inventory and inventory value.
A24: HOW THE CALCULATIONS WORK
A25: - Cost per Unit = (Purchase Cost + all 8 expenses) / Quantity Purchased. This is your true landed cost.
A26: - Selling Price = Cost per Unit x (1 + Markup %). Profit = Selling Price - Cost. Margin % = Profit / Selling Price. Markup % = Profit / Cost. Margin and markup are NOT the same thing — margin is profit as a % of price, markup is profit as a % of cost.
A27: - Business Settings' default markup/margin % flow into Retail & Wholesale Pricing, Profit Simulator, Dashboard and Product Profitability Summary automatically. Overwrite the pre-filled % on any of those sheets to test a different rate for one product without changing the global default.
A28: - Product Profitability Summary re-ranks itself automatically whenever costs or prices change - no manual sorting needed.
A29: - To add a new product: go to Product Costing and type into the next blank row under the table (row 22 onward) - formulas are already pre-built through row 21; copy row 21's formula cells down if you need more than 20 products.
A30: - Sheets are protected (no password) so formulas can't be overwritten by accident. Editable (yellow) cells still work normally. To make structural changes, use Review > Unprotect Sheet.
A32: CURRENCY NOTE
A33: Number formats default to a plain '#,##0.00' style. Set your currency label on the Business Settings sheet; if you'd like an actual currency symbol baked into the cell format, select the relevant cells and use Format Cells > Number > Currency in Excel.

Sheet Business Settings
A1: BUSINESS SETTINGS
A2: Edit the yellow input cells below. These defaults automatically flow into every other worksheet in this workbook.
A4: GENERAL
A5: Currency Label | B5: PHP | E5: For your reference / labeling (e.g. PHP, USD, EUR). See Read Me for currency formatting.
A6: VAT / Sales Tax Rate | B6: 0.12 | E6: Informational — apply manually where VAT is relevant to your pricing.
A8: RETAIL PRICING DEFAULTS
A9: Default Retail Markup % | B9: 0.35
A10: Default Retail Profit Margin % | B10: 0.25 | E10: Reference only; retail sheets calculate price from Markup %.
A12: WHOLESALE PRICING DEFAULTS
A13: Default Wholesale Markup % | B13: 0.18
A14: Default Wholesale Profit Margin % | B14: 0.15 | E14: Reference only; wholesale sheets calculate price from Markup %.
A16: FREIGHT & ALLOCATION
A17: Default Freight Allocation Method | B17: Per Unit | E17: Informational tag describing how you allocate freight in Product Costing.
A19: DEFAULT QUANTITY DISCOUNT TIERS
A20: Tier (Quantity Range) | B20: Min Qty | C20: Max Qty | D20: Discount %
A21: 1-9 units | B21: 1 | C21: 9 | D21: 0
A22: 10-24 units | B22: 10 | C22: 24 | D22: 0.03
A23: 25-49 units | B23: 25 | C23: 49 | D23: 0.05
A24: 50-99 units | B24: 50 | C24: 99 | D24: 0.08
A25: 100+ units | B25: 100 | C25: 100000 | D25: 0.12

Sheet Product Costing
A1: PRODUCT COSTING
A2: One row per product/purchase. Rename expense labels to match your business. Add new products in the next blank row below the table.
A3: Product Name | B3: Brand | C3: Category | D3: SKU | E3: Packaging Size | F3: Unit of Measure | G3: Units per Case | H3: Supplier Name | I3: Purchase Cost | J3: Quantity Purchased | K3: Expense 1 Name | L3: Expense 1 Amount | M3: Expense 2 Name | N3: Expense 2 Amount | O3: Expense 3 Name | P3: Expense 3 Amount | Q3: Expense 4 Name | R3: Expense 4 Amount | S3: Expense 5 Name | T3: Expense 5 Amount | U3: Expense 6 Name | V3: Expense 6 Amount | W3: Expense 7 Name | X3: Expense 7 Amount | Y3: Expense 8 Name | Z3: Expense 8 Amount | AA3: Total Expenses | AB3: Total Landed Cost | AC3: Cost per Unit
A4: 10W-40 Motor Oil 1L | B4: PetroMax | C4: Motor Oil | D4: MO-1040-1L | E4: 1 Liter | F4: Liter | G4: 12 | H4: Gulf Petroleum Supplier | I4: 24000 | J4: 1200 | K4: Freight | L4: 1200 | M4: Delivery | N4: 300 | O4: Packaging | P4: 150 | Q4: Storage | R4: 100 | S4: Labor | T4: 200 | U4: Fuel | V4: 250 | W4: Customs | X4: 0 | Y4: Miscellaneous | Z4: 50 | AA4: =IF($A4="","",L4+N4+P4+R4+T4+V4+X4+Z4) -> 2250 | AB4: =IF($A4="","",I4+AA4) -> 26250 | AC4: =IF($A4="","",IFERROR(AB4/J4,0)) -> 21.875
A5: 20W-50 Motor Oil 4L | B5: PetroMax | C5: Motor Oil | D5: MO-2050-4L | E5: 4 Liters | F5: Liter | G5: 4 | H5: Atlas Distributors | I5: 18000 | J5: 450 | K5: Freight | L5: 900 | M5: Delivery | N5: 250 | O5: Packaging | P5: 100 | Q5: Storage | R5: 80 | S5: Labor | T5: 150 | U5: Fuel | V5: 180 | W5: Customs | X5: 0 | Y5: Miscellaneous | Z5: 40 | AA5: =IF($A5="","",L5+N5+P5+R5+T5+V5+X5+Z5) -> 1700 | AB5: =IF($A5="","",I5+AA5) -> 19700 | AC5: =IF($A5="","",IFERROR(AB5/J5,0)) -> 43.777778
A6: Hydraulic Oil 20L Drum | B6: HydroTech | C6: Industrial Oil | D6: HYD-20L | E6: 20 Liters | F6: Drum | G6: 1 | H6: Coastal Oil Traders | I6: 32000 | J6: 160 | K6: Freight | L6: 1500 | M6: Delivery | N6: 400 | O6: Packaging | P6: 200 | Q6: Storage | R6: 150 | S6: Labor | T6: 300 | U6: Fuel | V6: 220 | W6: Customs | X6: 500 | Y6: Miscellaneous | Z6: 60 | AA6: =IF($A6="","",L6+N6+P6+R6+T6+V6+X6+Z6) -> 3330 | AB6: =IF($A6="","",I6+AA6) -> 35330 | AC6: =IF($A6="","",IFERROR(AB6/J6,0)) -> 220.8125
K7: Freight | M7: Delivery | O7: Packaging | Q7: Storage | S7: Labor | U7: Fuel | W7: Customs | Y7: Miscellaneous | AA7: =IF($A7="","",L7+N7+P7+R7+T7+V7+X7+Z7) | AB7: =IF($A7="","",I7+AA7) | AC7: =IF($A7="","",IFERROR(AB7/J7,0))
K8: Freight | M8: Delivery | O8: Packaging | Q8: Storage | S8: Labor | U8: Fuel | W8: Customs | Y8: Miscellaneous | AA8: =IF($A8="","",L8+N8+P8+R8+T8+V8+X8+Z8) | AB8: =IF($A8="","",I8+AA8) | AC8: =IF($A8="","",IFERROR(AB8/J8,0))
K9: Freight | M9: Delivery | O9: Packaging | Q9: Storage | S9: Labor | U9: Fuel | W9: Customs | Y9: Miscellaneous | AA9: =IF($A9="","",L9+N9+P9+R9+T9+V9+X9+Z9) | AB9: =IF($A9="","",I9+AA9) | AC9: =IF($A9="","",IFERROR(AB9/J9,0))
K10: Freight | M10: Delivery | O10: Packaging | Q10: Storage | S10: Labor | U10: Fuel | W10: Customs | Y10: Miscellaneous | AA10: =IF($A10="","",L10+N10+P10+R10+T10+V10+X10+Z10) | AB10: =IF($A10="","",I10+AA10) | AC10: =IF($A10="","",IFERROR(AB10/J10,0))
K11: Freight | M11: Delivery | O11: Packaging | Q11: Storage | S11: Labor | U11: Fuel | W11: Customs | Y11: Miscellaneous | AA11: =IF($A11="","",L11+N11+P11+R11+T11+V11+X11+Z11) | AB11: =IF($A11="","",I11+AA11) | AC11: =IF($A11="","",IFERROR(AB11/J11,0))
K12: Freight | M12: Delivery | O12: Packaging | Q12: Storage | S12: Labor | U12: Fuel | W12: Customs | Y12: Miscellaneous | AA12: =IF($A12="","",L12+N12+P12+R12+T12+V12+X12+Z12) | AB12: =IF($A12="","",I12+AA12) | AC12: =IF($A12="","",IFERROR(AB12/J12,0))
K13: Freight | M13: Delivery | O13: Packaging | Q13: Storage | S13: Labor | U13: Fuel | W13: Customs | Y13: Miscellaneous | AA13: =IF($A13="","",L13+N13+P13+R13+T13+V13+X13+Z13) | AB13: =IF($A13="","",I13+AA13) | AC13: =IF($A13="","",IFERROR(AB13/J13,0))
K14: Freight | M14: Delivery | O14: Packaging | Q14: Storage | S14: Labor | U14: Fuel | W14: Customs | Y14: Miscellaneous | AA14: =IF($A14="","",L14+N14+P14+R14+T14+V14+X14+Z14) | AB14: =IF($A14="","",I14+AA14) | AC14: =IF($A14="","",IFERROR(AB14/J14,0))
K15: Freight | M15: Delivery | O15: Packaging | Q15: Storage | S15: Labor | U15: Fuel | W15: Customs | Y15: Miscellaneous | AA15: =IF($A15="","",L15+N15+P15+R15+T15+V15+X15+Z15) | AB15: =IF($A15="","",I15+AA15) | AC15: =IF($A15="","",IFERROR(AB15/J15,0))
K16: Freight | M16: Delivery | O16: Packaging | Q16: Storage | S16: Labor | U16: Fuel | W16: Customs | Y16: Miscellaneous | AA16: =IF($A16="","",L16+N16+P16+R16+T16+V16+X16+Z16) | AB16: =IF($A16="","",I16+AA16) | AC16: =IF($A16="","",IFERROR(AB16/J16,0))
K17: Freight | M17: Delivery | O17: Packaging | Q17: Storage | S17: Labor | U17: Fuel | W17: Customs | Y17: Miscellaneous | AA17: =IF($A17="","",L17+N17+P17+R17+T17+V17+X17+Z17) | AB17: =IF($A17="","",I17+AA17) | AC17: =IF($A17="","",IFERROR(AB17/J17,0))
K18: Freight | M18: Delivery | O18: Packaging | Q18: Storage | S18: Labor | U18: Fuel | W18: Customs | Y18: Miscellaneous | AA18: =IF($A18="","",L18+N18+P18+R18+T18+V18+X18+Z18) | AB18: =IF($A18="","",I18+AA18) | AC18: =IF($A18="","",IFERROR(AB18/J18,0))
... K23: Freight | M23: Delivery | O23: Packaging | Q23: Storage | S23: Labor | U23: Fuel | W23: Customs | Y23: Miscellaneous | AA23: =IF($A23="","",L23+N23+P23+R23+T23+V23+X23+Z23) | AB23: =IF($A23="","",I23+AA23) | AC23: =IF($A23="","",IFERROR(AB23/J23,0))

Sheet Pricing Calculator
A1: PRICING CALCULATOR
A2: Three independent calculators. Fill in the yellow inputs for each mode.
A4: MODE 1 - COST TO SELLING PRICE
A5: Purchase Cost per Unit | B5: 150 | D5: Enter what the product costs you and how much profit per unit you want to earn.
A6: Total Expenses per Unit | B6: 25
A7: Desired Profit per Unit | B7: 50
A8: Total Cost per Unit | B8: =B5+B6 -> 175
A9: Required Selling Price | B9: =B8+B7 -> 225
A10: Profit | B10: =B9-B8 -> 50
A11: Profit Margin % | B11: =IFERROR(B10/B9,0) -> 0.22222222
A12: Markup % | B12: =IFERROR(B10/B8,0) -> 0.28571429
A15: MODE 2 - SELLING PRICE TO MAXIMUM PURCHASE COST
A16: Selling Price | B16: 250 | D16: Use this to test whether a supplier's quoted price still lets you hit your selling price and profit target.
A17: Expenses per Unit | B17: 25
A18: Desired Profit per Unit | B18: 50
A19: Maximum Purchase Cost Allowed | B19: =B16-B17-B18 -> 175
A20: Implied Margin % | B20: =IFERROR(B18/B16,0) -> 0.2
A21: Implied Markup % | B21: =IFERROR(B18/(B19+B17),0) -> 0.25
A24: MODE 3 - TARGET PROFIT
A25: Purchase Cost per Unit | B25: 150 | D25: Same idea as Mode 1, but framed around a total target profit figure you set (e.g. per container/shipment) rather than a markup.
A26: Expenses per Unit | B26: 25
A27: Target Profit Amount per Unit | B27: 75
A28: Total Cost per Unit | B28: =B25+B26 -> 175
A29: Required Selling Price | B29: =B28+B27 -> 250
A30: Profit Margin % | B30: =IFERROR(B27/B29,0) -> 0.3
A31: Markup % | B31: =IFERROR(B27/B28,0) -> 0.42857143

Sheet Retail & Wholesale Pricing
A1: RETAIL & WHOLESALE PRICING
A2: Enter the product's cost once - retail, wholesale, and quantity-discount pricing all update automatically.
A4: PRODUCT COST (enter once)
A5: Purchase Cost per Unit | B5: 150
A6: Total Expenses per Unit | B6: 25
A7: Total Cost per Unit | B7: =B5+B6 -> 175
A9: RETAIL PRICING | D9: WHOLESALE PRICING
A10: Retail Markup % | B10: =Default_Retail_Markup -> 0.35 | D10: Minimum Order Quantity (MOQ) | E10: 50
A11: Retail Selling Price | B11: =$B$7*(1+B10) -> 236.25 | D11: Wholesale Markup % | E11: =Default_Wholesale_Markup -> 0.18
A12: Retail Profit | B12: =B11-$B$7 -> 61.25 | D12: Wholesale Selling Price | E12: =$B$7*(1+E11) -> 206.5
A13: Retail Margin % | B13: =IFERROR(B12/B11,0) -> 0.25925926 | D13: Wholesale Profit | E13: =E12-$B$7 -> 31.5
A14: Retail Markup % (check) | B14: =IFERROR(B12/$B$7,0) -> 0.35 | D14: Wholesale Margin % | E14: =IFERROR(E13/E12,0) -> 0.15254237
D15: Wholesale Markup % (check) | E15: =IFERROR(E13/$B$7,0) -> 0.18
A17: QUANTITY DISCOUNT PRICING (applied to Wholesale Selling Price)
A18: Quantity Tier | B18: Discount % | C18: Final Selling Price | D18: Profit | E18: Margin %
A19: ='Business Settings'!A21 -> 1-9 units | B19: ='Business Settings'!D21 -> 0 | C19: =$E$12*(1-B19) -> 206.5 | D19: =C19-$B$7 -> 31.5 | E19: =IFERROR(D19/C19,0) -> 0.15254237
A20: ='Business Settings'!A22 -> 10-24 units | B20: ='Business Settings'!D22 -> 0.03 | C20: =$E$12*(1-B20) -> 200.305 | D20: =C20-$B$7 -> 25.305 | E20: =IFERROR(D20/C20,0) -> 0.12633234
A21: ='Business Settings'!A23 -> 25-49 units | B21: ='Business Settings'!D23 -> 0.05 | C21: =$E$12*(1-B21) -> 196.175 | D21: =C21-$B$7 -> 21.175 | E21: =IFERROR(D21/C21,0) -> 0.10793934
A22: ='Business Settings'!A24 -> 50-99 units | B22: ='Business Settings'!D24 -> 0.08 | C22: =$E$12*(1-B22) -> 189.98 | D22: =C22-$B$7 -> 14.98 | E22: =IFERROR(D22/C22,0) -> 0.078850405
A23: ='Business Settings'!A25 -> 100+ units | B23: ='Business Settings'!D25 -> 0.12 | C23: =$E$12*(1-B23) -> 181.72 | D23: =C23-$B$7 -> 6.72 | E23: =IFERROR(D23/C23,0) -> 0.036979969

Sheet Supplier Comparison
A1: SUPPLIER COMPARISON
A2: Compare up to 4 supplier quotes for the same product. Best values are highlighted automatically.
A4: COMPARISON ASSUMPTIONS (applied to every supplier)
A5: Assumed Retail Selling Price | B5: 250
A6: Assumed Wholesale Selling Price | B6: 210
A7: Quantity Purchased (per quote) | B7: 1000
A9: Metric | B9: Supplier A | C9: Supplier B | D9: Supplier C | E9: Supplier D
A10: Supplier Name | B10: Gulf Petroleum Supplier | C10: Atlas Distributors | D10: Coastal Oil Traders
A11: Purchase Cost (total) | B11: 24000 | C11: 23500 | D11: 24800
A12: Freight | B12: 1200 | C12: 1000 | D12: 1500
A13: Other Charges | B13: 400 | C13: 450 | D13: 350
A14: Total Landed Cost | B14: =IF(B11="","",B11+B12+B13) -> 25600 | C14: =IF(C11="","",C11+C12+C13) -> 24950 | D14: =IF(D11="","",D11+D12+D13) -> 26650 | E14: =IF(E11="","",E11+E12+E13)
A15: Cost per Unit | B15: =IF(B14="","",IFERROR(B14/$B$7,0)) -> 25.6 | C15: =IF(C14="","",IFERROR(C14/$B$7,0)) -> 24.95 | D15: =IF(D14="","",IFERROR(D14/$B$7,0)) -> 26.65 | E15: =IF(E14="","",IFERROR(E14/$B$7,0))
A16: Retail Profit | B16: =IF(B15="","",$B$5-B15) -> 224.4 | C16: =IF(C15="","",$B$5-C15) -> 225.05 | D16: =IF(D15="","",$B$5-D15) -> 223.35 | E16: =IF(E15="","",$B$5-E15)
A17: Wholesale Profit | B17: =IF(B15="","",$B$6-B15) -> 184.4 | C17: =IF(C15="","",$B$6-C15) -> 185.05 | D17: =IF(D15="","",$B$6-D15) -> 183.35 | E17: =IF(E15="","",$B$6-E15)
A18: Combined Profit (Retail + Wholesale) | B18: =IF(B16="","",B16+B17) -> 408.8 | C18: =IF(C16="","",C16+C17) -> 410.1 | D18: =IF(D16="","",D16+D17) -> 406.7 | E18: =IF(E16="","",E16+E17)
A20: BEST SUPPLIER SUMMARY
A21: Lowest Cost Supplier | B21: =INDEX($B$10:$E$10,MATCH(MIN($B$15:$E$15),$B$15:$E$15,0)) -> Atlas Distributors
A22: Highest Retail Profit Supplier | B22: =INDEX($B$10:$E$10,MATCH(MAX($B$16:$E$16),$B$16:$E$16,0)) -> Atlas Distributors
A23: Highest Wholesale Profit Supplier | B23: =INDEX($B$10:$E$10,MATCH(MAX($B$17:$E$17),$B$17:$E$17,0)) -> Atlas Distributors
A24: Best Overall Supplier (Retail + Wholesale) | B24: =INDEX($B$10:$E$10,MATCH(MAX($B$18:$E$18),$B$18:$E$18,0)) -> Atlas Distributors

Sheet Profit Simulator
A1: PROFIT SIMULATOR
A2: Change any cost, expense or markup below to instantly see the effect on price, profit and margin.
A4: SCENARIO INPUTS
A5: Purchase Cost per Unit | B5: 150
A6: Freight per Unit | B6: 15
A7: Other Expenses per Unit | B7: 10
A8: Cost per Unit | B8: =B5+B6+B7 -> 175
A9: Desired Profit per Unit | B9: 50
A10: Retail Markup % | B10: =Default_Retail_Markup -> 0.35
A11: Wholesale Markup % | B11: =Default_Wholesale_Markup -> 0.18
A13: RESULTS
A14: New Selling Price (Cost + Desired Profit) | B14: =B8+B9 -> 225
A15: New Retail Selling Price (Markup-based) | B15: =B8*(1+B10) -> 236.25
A16: New Wholesale Selling Price (Markup-based) | B16: =B8*(1+B11) -> 206.5
A17: Profit @ Target-Profit Price | B17: =B14-B8 -> 50
A18: Retail Profit | B18: =B15-B8 -> 61.25
A19: Wholesale Profit | B19: =B16-B8 -> 31.5
A20: Retail Margin % | B20: =IFERROR(B18/B15,0) -> 0.25925926
A21: Wholesale Margin % | B21: =IFERROR(B19/B16,0) -> 0.15254237
A22: Cost per Unit (reference) | B22: =B8 -> 175

Sheet Sensitivity Analysis
A1: SENSITIVITY ANALYSIS
A2: See how profit, margin and markup move when purchase cost, expenses, or selling price change.
A4: BASE CASE
A5: Base Purchase Cost per Unit | B5: 150
A6: Base Expenses per Unit | B6: 25
A7: Base Selling Price | B7: 250
A8: Base Total Cost | B8: =B5+B6 -> 175
A9: Base Profit | B9: =B7-B8 -> 75
A10: Base Margin % | B10: =IFERROR(B9/B7,0) -> 0.3
A11: Base Markup % | B11: =IFERROR(B9/B8,0) -> 0.42857143
A13: PURCHASE COST SENSITIVITY (at Base Selling Price)
A14: Change % | B14: New Purchase Cost | C14: New Expenses | D14: New Total Cost / New Selling Price | E14: Profit | F14: Margin % / Markup %
A15: 0.05 | B15: =$B$5*(1+A15) -> 157.5 | C15: =$B$6 -> 25 | D15: =B15+C15 -> 182.5 | E15: =$B$7-D15 -> 67.5 | F15: =IFERROR(E15/$B$7,0) -> 0.27
A16: 0.1 | B16: =$B$5*(1+A16) -> 165 | C16: =$B$6 -> 25 | D16: =B16+C16 -> 190 | E16: =$B$7-D16 -> 60 | F16: =IFERROR(E16/$B$7,0) -> 0.24
A17: 0.15 | B17: =$B$5*(1+A17) -> 172.5 | C17: =$B$6 -> 25 | D17: =B17+C17 -> 197.5 | E17: =$B$7-D17 -> 52.5 | F17: =IFERROR(E17/$B$7,0) -> 0.21
A18: 0.2 | B18: =$B$5*(1+A18) -> 180 | C18: =$B$6 -> 25 | D18: =B18+C18 -> 205 | E18: =$B$7-D18 -> 45 | F18: =IFERROR(E18/$B$7,0) -> 0.18
A20: EXPENSE INCREASE SENSITIVITY (at Base Selling Price)
A21: Change % | B21: New Purchase Cost | C21: New Expenses | D21: New Total Cost / New Selling Price | E21: Profit | F21: Margin % / Markup %
A22: 0.05 | B22: =$B$5 -> 150 | C22: =$B$6*(1+A22) -> 26.25 | D22: =B22+C22 -> 176.25 | E22: =$B$7-D22 -> 73.75 | F22: =IFERROR(E22/$B$7,0) -> 0.295
A23: 0.1 | B23: =$B$5 -> 150 | C23: =$B$6*(1+A23) -> 27.5 | D23: =B23+C23 -> 177.5 | E23: =$B$7-D23 -> 72.5 | F23: =IFERROR(E23/$B$7,0) -> 0.29
A24: 0.15 | B24: =$B$5 -> 150 | C24: =$B$6*(1+A24) -> 28.75 | D24: =B24+C24 -> 178.75 | E24: =$B$7-D24 -> 71.25 | F24: =IFERROR(E24/$B$7,0) -> 0.285
A25: 0.2 | B25: =$B$5 -> 150 | C25: =$B$6*(1+A25) -> 30 | D25: =B25+C25 -> 180 | E25: =$B$7-D25 -> 70 | F25: =IFERROR(E25/$B$7,0) -> 0.28
A27: SELLING PRICE SENSITIVITY (at Base Total Cost)
A28: Change % | B28: New Purchase Cost | C28: New Expenses | D28: New Total Cost / New Selling Price | E28: Profit | F28: Margin % / Markup %
A29: -0.1 | B29: =$B$5 -> 150 | C29: =$B$6 -> 25 | D29: =$B$7*(1+A29) -> 225 | E29: =D29-$B$8 -> 50 | F29: =IFERROR(E29/D29,0) -> 0.22222222
A30: -0.05 | B30: =$B$5 -> 150 | C30: =$B$6 -> 25 | D30: =$B$7*(1+A30) -> 237.5 | E30: =D30-$B$8 -> 62.5 | F30: =IFERROR(E30/D30,0) -> 0.26315789
A31: 0.05 | B31: =$B$5 -> 150 | C31: =$B$6 -> 25 | D31: =$B$7*(1+A31) -> 262.5 | E31: =D31-$B$8 -> 87.5 | F31: =IFERROR(E31/D31,0) -> 0.33333333
A32: 0.1 | B32: =$B$5 -> 150 | C32: =$B$6 -> 25 | D32: =$B$7*(1+A32) -> 275 | E32: =D32-$B$8 -> 100 | F32: =IFERROR(E32/D32,0) -> 0.36363636

Sheet Dashboard
A1: DASHBOARD
A2: Pick a product to see its full cost & pricing picture in one place.
H3: Helper cells - do not edit
A4: Select Product: | B4: 10W-40 Motor Oil 1L | H4: =IFERROR(MATCH($B$4,'Product Costing'!$A$4:$A$23,0),"") -> 1
A5: Brand | B5: =IF($H$4="","",INDEX('Product Costing'!$B$4:$B$23,$H$4)) -> PetroMax
A6: Category | B6: =IF($H$4="","",INDEX('Product Costing'!$C$4:$C$23,$H$4)) -> Motor Oil
A7: Supplier | B7: =IF($H$4="","",INDEX('Product Costing'!$H$4:$H$23,$H$4)) -> Gulf Petroleum Supplier
A9: KEY PERFORMANCE INDICATORS
A10: Total Landed Cost | B10: =IF($H$4="","",INDEX('Product Costing'!$AB$4:$AB$23,$H$4)) -> 26250
A11: Cost per Unit | B11: =IF($H$4="","",INDEX('Product Costing'!$AC$4:$AC$23,$H$4)) -> 21.875
A12: Retail Selling Price | B12: =IF($B$11="","",$B$11*(1+Default_Retail_Markup)) -> 29.53125
A13: Wholesale Selling Price | B13: =IF($B$11="","",$B$11*(1+Default_Wholesale_Markup)) -> 25.8125
A14: Retail Profit | B14: =IF($B$11="","",B12-B11) -> 7.65625
A15: Wholesale Profit | B15: =IF($B$11="","",B13-B11) -> 3.9375
A16: Retail Margin % | B16: =IF($B$11="","",IFERROR(B14/B12,0)) -> 0.25925926
A17: Wholesale Margin % | B17: =IF($B$11="","",IFERROR(B15/B13,0)) -> 0.15254237
A18: Markup % (Retail) | B18: =IF($B$11="","",IFERROR(B14/B11,0)) -> 0.35
A19: Break-even Selling Price | B19: =B11 -> 21.875
A22: CHART DATA - PROFIT COMPARISON
A23: Metric | B23: Profit
A24: Retail Profit | B24: =B14 -> 7.65625
A25: Wholesale Profit | B25: =B15 -> 3.9375
A27: EXPENSE BREAKDOWN (Selected Product)
A28: Expense | B28: Amount
A29: =IF($H$4="","",INDEX('Product Costing'!$K$4:$K$23,$H$4)) -> Freight | B29: =IF($H$4="","",INDEX('Product Costing'!$L$4:$L$23,$H$4)) -> 1200
A30: =IF($H$4="","",INDEX('Product Costing'!$M$4:$M$23,$H$4)) -> Delivery | B30: =IF($H$4="","",INDEX('Product Costing'!$N$4:$N$23,$H$4)) -> 300
A31: =IF($H$4="","",INDEX('Product Costing'!$O$4:$O$23,$H$4)) -> Packaging | B31: =IF($H$4="","",INDEX('Product Costing'!$P$4:$P$23,$H$4)) -> 150
A32: =IF($H$4="","",INDEX('Product Costing'!$Q$4:$Q$23,$H$4)) -> Storage | B32: =IF($H$4="","",INDEX('Product Costing'!$R$4:$R$23,$H$4)) -> 100
A33: =IF($H$4="","",INDEX('Product Costing'!$S$4:$S$23,$H$4)) -> Labor | B33: =IF($H$4="","",INDEX('Product Costing'!$T$4:$T$23,$H$4)) -> 200
A34: =IF($H$4="","",INDEX('Product Costing'!$U$4:$U$23,$H$4)) -> Fuel | B34: =IF($H$4="","",INDEX('Product Costing'!$V$4:$V$23,$H$4)) -> 250
A35: =IF($H$4="","",INDEX('Product Costing'!$W$4:$W$23,$H$4)) -> Customs | B35: =IF($H$4="","",INDEX('Product Costing'!$X$4:$X$23,$H$4)) -> 0
A36: =IF($H$4="","",INDEX('Product Costing'!$Y$4:$Y$23,$H$4)) -> Miscellaneous | B36: =IF($H$4="","",INDEX('Product Costing'!$Z$4:$Z$23,$H$4)) -> 50

Sheet Break-even Calculator
A1: BREAK-EVEN CALCULATOR
A2: What's the minimum selling price where you don't lose money?
A4: INPUTS
A5: Purchase Cost per Unit | B5: 150
A6: Expenses per Unit | B6: 25
A7: Current Selling Price | B7: 250
A9: RESULTS
A10: Break-even Selling Price | B10: =B5+B6 -> 175 | D10: The selling price at which profit is exactly zero.
A11: Profit at Current Selling Price | B11: =B7-B10 -> 75
A12: Safety Margin % | B12: =IFERROR((B7-B10)/B7,0) -> 0.3 | D12: How much your current price could drop before you hit break-even.

Sheet Price Negotiation Tool
A1: PRICE NEGOTIATION TOOL
A2: See how a new supplier quote changes your cost, profit, and required selling price.
A4: CURRENT SITUATION
A5: Current Purchase Cost per Unit | B5: 150
A6: Expenses per Unit | B6: 25
A7: Current Selling Price | B7: 250
A8: Current Total Cost | B8: =B5+B6 -> 175
A9: Current Profit | B9: =B7-B8 -> 75
A10: Current Margin % | B10: =IFERROR(B9/B7,0) -> 0.3
A12: NEW SUPPLIER OFFER
A13: New Purchase Cost per Unit | B13: 165
A14: New Total Cost | B14: =B13+B6 -> 190
A15: New Profit (at current Selling Price) | B15: =B7-B14 -> 60
A16: New Margin % (at current Selling Price) | B16: =IFERROR(B15/B7,0) -> 0.24
A17: New Markup % | B17: =IFERROR(B15/B14,0) -> 0.31578947
A18: Profit Impact ($ change) | B18: =B15-B9 -> -15
A19: Selling Price to Maintain Current Margin % | B19: =IFERROR(B14/(1-B10),0) -> 271.42857 | D19: The price you'd need to charge at the new cost to keep the same margin % you have today.

Sheet Reverse Cost Calculator
A1: REVERSE COST CALCULATOR
A2: Work backward from a customer's budget and your desired profit to find the maximum you can pay a supplier.
A4: INPUTS
A5: Customer Budget (Target Selling Price) | B5: 250
A6: Expenses per Unit | B6: 25
A7: Desired Profit per Unit | B7: 50
A9: RESULTS
A10: Maximum Purchase Cost Allowed | B10: =B5-B6-B7 -> 175 | D10: Use this figure as your ceiling when negotiating a supplier price.
A11: Resulting Margin % | B11: =IFERROR(B7/B5,0) -> 0.2
A12: Resulting Markup % | B12: =IFERROR(B7/(B10+B6),0) -> 0.25

Sheet Product Profitability Summary
A1: PRODUCT PROFITABILITY SUMMARY | K1: Populated Count
A2: All products from Product Costing, ranked automatically from highest to lowest retail profit. Re-ranks itself whenever costs or markups change. | K2: =COUNTIF($L$5:$L$24,"?*") -> 3
A4: Rank | B4: Product | C4: Cost per Unit | D4: Retail Price | E4: Wholesale Price | F4: Retail Profit | G4: Wholesale Profit | H4: Margin % | I4: Markup % | L4: HELPER - DO NOT EDIT (raw data pulled from Product Costing)
A5: =ROW()-4 -> 1 | B5: =IF($A5>$K$2,"",INDEX($L$5:$L$24,$J5)) -> Hydraulic Oil 20L Drum | C5: =IF($A5>$K$2,"",INDEX($M$5:$M$24,$J5)) -> 220.8125 | D5: =IF($A5>$K$2,"",INDEX($N$5:$N$24,$J5)) -> 298.09688 | E5: =IF($A5>$K$2,"",INDEX($O$5:$O$24,$J5)) -> 260.55875 | F5: =IF($A5>$K$2,"",INDEX($P$5:$P$24,$J5)) -> 77.284375 | G5: =IF($A5>$K$2,"",INDEX($Q$5:$Q$24,$J5)) -> 39.74625 | H5: =IF($A5>$K$2,"",INDEX($R$5:$R$24,$J5)) -> 0.25925926 | I5: =IF($A5>$K$2,"",INDEX($S$5:$S$24,$J5)) -> 0.35 | J5: =MATCH(LARGE($T$5:$T$24,A5),$T$5:$T$24,0) -> 3 | L5: ='Product Costing'!A4&"" -> 10W-40 Motor Oil 1L | M5: ='Product Costing'!AC4 -> 21.875 | N5: =IF(L5="","",M5*(1+Default_Retail_Markup)) -> 29.53125 | O5: =IF(L5="","",M5*(1+Default_Wholesale_Markup)) -> 25.8125 | P5: =IF(L5="","",N5-M5) -> 7.65625 | Q5: =IF(L5="","",O5-M5) -> 3.9375 | R5: =IF(L5="","",IFERROR(P5/N5,0)) -> 0.25925926 | S5: =IF(L5="","",IFERROR(P5/M5,0)) -> 0.35 | T5: =IF(L5="",-999999999,P5+(1000-ROW())*0.0000001) -> 7.6563495
A6: =ROW()-4 -> 2 | B6: =IF($A6>$K$2,"",INDEX($L$5:$L$24,$J6)) -> 20W-50 Motor Oil 4L | C6: =IF($A6>$K$2,"",INDEX($M$5:$M$24,$J6)) -> 43.777778 | D6: =IF($A6>$K$2,"",INDEX($N$5:$N$24,$J6)) -> 59.1 | E6: =IF($A6>$K$2,"",INDEX($O$5:$O$24,$J6)) -> 51.657778 | F6: =IF($A6>$K$2,"",INDEX($P$5:$P$24,$J6)) -> 15.322222 | G6: =IF($A6>$K$2,"",INDEX($Q$5:$Q$24,$J6)) -> 7.88 | H6: =IF($A6>$K$2,"",INDEX($R$5:$R$24,$J6)) -> 0.25925926 | I6: =IF($A6>$K$2,"",INDEX($S$5:$S$24,$J6)) -> 0.35 | J6: =MATCH(LARGE($T$5:$T$24,A6),$T$5:$T$24,0) -> 2 | L6: ='Product Costing'!A5&"" -> 20W-50 Motor Oil 4L | M6: ='Product Costing'!AC5 -> 43.777778 | N6: =IF(L6="","",M6*(1+Default_Retail_Markup)) -> 59.1 | O6: =IF(L6="","",M6*(1+Default_Wholesale_Markup)) -> 51.657778 | P6: =IF(L6="","",N6-M6) -> 15.322222 | Q6: =IF(L6="","",O6-M6) -> 7.88 | R6: =IF(L6="","",IFERROR(P6/N6,0)) -> 0.25925926 | S6: =IF(L6="","",IFERROR(P6/M6,0)) -> 0.35 | T6: =IF(L6="",-999999999,P6+(1000-ROW())*0.0000001) -> 15.322322
A7: =ROW()-4 -> 3 | B7: =IF($A7>$K$2,"",INDEX($L$5:$L$24,$J7)) -> 10W-40 Motor Oil 1L | C7: =IF($A7>$K$2,"",INDEX($M$5:$M$24,$J7)) -> 21.875 | D7: =IF($A7>$K$2,"",INDEX($N$5:$N$24,$J7)) -> 29.53125 | E7: =IF($A7>$K$2,"",INDEX($O$5:$O$24,$J7)) -> 25.8125 | F7: =IF($A7>$K$2,"",INDEX($P$5:$P$24,$J7)) -> 7.65625 | G7: =IF($A7>$K$2,"",INDEX($Q$5:$Q$24,$J7)) -> 3.9375 | H7: =IF($A7>$K$2,"",INDEX($R$5:$R$24,$J7)) -> 0.25925926 | I7: =IF($A7>$K$2,"",INDEX($S$5:$S$24,$J7)) -> 0.35 | J7: =MATCH(LARGE($T$5:$T$24,A7),$T$5:$T$24,0) -> 1 | L7: ='Product Costing'!A6&"" -> Hydraulic Oil 20L Drum | M7: ='Product Costing'!AC6 -> 220.8125 | N7: =IF(L7="","",M7*(1+Default_Retail_Markup)) -> 298.09688 | O7: =IF(L7="","",M7*(1+Default_Wholesale_Markup)) -> 260.55875 | P7: =IF(L7="","",N7-M7) -> 77.284375 | Q7: =IF(L7="","",O7-M7) -> 39.74625 | R7: =IF(L7="","",IFERROR(P7/N7,0)) -> 0.25925926 | S7: =IF(L7="","",IFERROR(P7/M7,0)) -> 0.35 | T7: =IF(L7="",-999999999,P7+(1000-ROW())*0.0000001) -> 77.284474
A8: =ROW()-4 -> 4 | B8: =IF($A8>$K$2,"",INDEX($L$5:$L$24,$J8)) | C8: =IF($A8>$K$2,"",INDEX($M$5:$M$24,$J8)) | D8: =IF($A8>$K$2,"",INDEX($N$5:$N$24,$J8)) | E8: =IF($A8>$K$2,"",INDEX($O$5:$O$24,$J8)) | F8: =IF($A8>$K$2,"",INDEX($P$5:$P$24,$J8)) | G8: =IF($A8>$K$2,"",INDEX($Q$5:$Q$24,$J8)) | H8: =IF($A8>$K$2,"",INDEX($R$5:$R$24,$J8)) | I8: =IF($A8>$K$2,"",INDEX($S$5:$S$24,$J8)) | J8: =MATCH(LARGE($T$5:$T$24,A8),$T$5:$T$24,0) -> 4 | L8: ='Product Costing'!A7&"" | M8: ='Product Costing'!AC7 | N8: =IF(L8="","",M8*(1+Default_Retail_Markup)) | O8: =IF(L8="","",M8*(1+Default_Wholesale_Markup)) | P8: =IF(L8="","",N8-M8) | Q8: =IF(L8="","",O8-M8) | R8: =IF(L8="","",IFERROR(P8/N8,0)) | S8: =IF(L8="","",IFERROR(P8/M8,0)) | T8: =IF(L8="",-999999999,P8+(1000-ROW())*0.0000001) -> -999999999
A9: =ROW()-4 -> 5 | B9: =IF($A9>$K$2,"",INDEX($L$5:$L$24,$J9)) | C9: =IF($A9>$K$2,"",INDEX($M$5:$M$24,$J9)) | D9: =IF($A9>$K$2,"",INDEX($N$5:$N$24,$J9)) | E9: =IF($A9>$K$2,"",INDEX($O$5:$O$24,$J9)) | F9: =IF($A9>$K$2,"",INDEX($P$5:$P$24,$J9)) | G9: =IF($A9>$K$2,"",INDEX($Q$5:$Q$24,$J9)) | H9: =IF($A9>$K$2,"",INDEX($R$5:$R$24,$J9)) | I9: =IF($A9>$K$2,"",INDEX($S$5:$S$24,$J9)) | J9: =MATCH(LARGE($T$5:$T$24,A9),$T$5:$T$24,0) -> 4 | L9: ='Product Costing'!A8&"" | M9: ='Product Costing'!AC8 | N9: =IF(L9="","",M9*(1+Default_Retail_Markup)) | O9: =IF(L9="","",M9*(1+Default_Wholesale_Markup)) | P9: =IF(L9="","",N9-M9) | Q9: =IF(L9="","",O9-M9) | R9: =IF(L9="","",IFERROR(P9/N9,0)) | S9: =IF(L9="","",IFERROR(P9/M9,0)) | T9: =IF(L9="",-999999999,P9+(1000-ROW())*0.0000001) -> -999999999
A10: =ROW()-4 -> 6 | B10: =IF($A10>$K$2,"",INDEX($L$5:$L$24,$J10)) | C10: =IF($A10>$K$2,"",INDEX($M$5:$M$24,$J10)) | D10: =IF($A10>$K$2,"",INDEX($N$5:$N$24,$J10)) | E10: =IF($A10>$K$2,"",INDEX($O$5:$O$24,$J10)) | F10: =IF($A10>$K$2,"",INDEX($P$5:$P$24,$J10)) | G10: =IF($A10>$K$2,"",INDEX($Q$5:$Q$24,$J10)) | H10: =IF($A10>$K$2,"",INDEX($R$5:$R$24,$J10)) | I10: =IF($A10>$K$2,"",INDEX($S$5:$S$24,$J10)) | J10: =MATCH(LARGE($T$5:$T$24,A10),$T$5:$T$24,0) -> 4 | L10: ='Product Costing'!A9&"" | M10: ='Product Costing'!AC9 | N10: =IF(L10="","",M10*(1+Default_Retail_Markup)) | O10: =IF(L10="","",M10*(1+Default_Wholesale_Markup)) | P10: =IF(L10="","",N10-M10) | Q10: =IF(L10="","",O10-M10) | R10: =IF(L10="","",IFERROR(P10/N10,0)) | S10: =IF(L10="","",IFERROR(P10/M10,0)) | T10: =IF(L10="",-999999999,P10+(1000-ROW())*0.0000001) -> -999999999
A11: =ROW()-4 -> 7 | B11: =IF($A11>$K$2,"",INDEX($L$5:$L$24,$J11)) | C11: =IF($A11>$K$2,"",INDEX($M$5:$M$24,$J11)) | D11: =IF($A11>$K$2,"",INDEX($N$5:$N$24,$J11)) | E11: =IF($A11>$K$2,"",INDEX($O$5:$O$24,$J11)) | F11: =IF($A11>$K$2,"",INDEX($P$5:$P$24,$J11)) | G11: =IF($A11>$K$2,"",INDEX($Q$5:$Q$24,$J11)) | H11: =IF($A11>$K$2,"",INDEX($R$5:$R$24,$J11)) | I11: =IF($A11>$K$2,"",INDEX($S$5:$S$24,$J11)) | J11: =MATCH(LARGE($T$5:$T$24,A11),$T$5:$T$24,0) -> 4 | L11: ='Product Costing'!A10&"" | M11: ='Product Costing'!AC10 | N11: =IF(L11="","",M11*(1+Default_Retail_Markup)) | O11: =IF(L11="","",M11*(1+Default_Wholesale_Markup)) | P11: =IF(L11="","",N11-M11) | Q11: =IF(L11="","",O11-M11) | R11: =IF(L11="","",IFERROR(P11/N11,0)) | S11: =IF(L11="","",IFERROR(P11/M11,0)) | T11: =IF(L11="",-999999999,P11+(1000-ROW())*0.0000001) -> -999999999
A12: =ROW()-4 -> 8 | B12: =IF($A12>$K$2,"",INDEX($L$5:$L$24,$J12)) | C12: =IF($A12>$K$2,"",INDEX($M$5:$M$24,$J12)) | D12: =IF($A12>$K$2,"",INDEX($N$5:$N$24,$J12)) | E12: =IF($A12>$K$2,"",INDEX($O$5:$O$24,$J12)) | F12: =IF($A12>$K$2,"",INDEX($P$5:$P$24,$J12)) | G12: =IF($A12>$K$2,"",INDEX($Q$5:$Q$24,$J12)) | H12: =IF($A12>$K$2,"",INDEX($R$5:$R$24,$J12)) | I12: =IF($A12>$K$2,"",INDEX($S$5:$S$24,$J12)) | J12: =MATCH(LARGE($T$5:$T$24,A12),$T$5:$T$24,0) -> 4 | L12: ='Product Costing'!A11&"" | M12: ='Product Costing'!AC11 | N12: =IF(L12="","",M12*(1+Default_Retail_Markup)) | O12: =IF(L12="","",M12*(1+Default_Wholesale_Markup)) | P12: =IF(L12="","",N12-M12) | Q12: =IF(L12="","",O12-M12) | R12: =IF(L12="","",IFERROR(P12/N12,0)) | S12: =IF(L12="","",IFERROR(P12/M12,0)) | T12: =IF(L12="",-999999999,P12+(1000-ROW())*0.0000001) -> -999999999
A13: =ROW()-4 -> 9 | B13: =IF($A13>$K$2,"",INDEX($L$5:$L$24,$J13)) | C13: =IF($A13>$K$2,"",INDEX($M$5:$M$24,$J13)) | D13: =IF($A13>$K$2,"",INDEX($N$5:$N$24,$J13)) | E13: =IF($A13>$K$2,"",INDEX($O$5:$O$24,$J13)) | F13: =IF($A13>$K$2,"",INDEX($P$5:$P$24,$J13)) | G13: =IF($A13>$K$2,"",INDEX($Q$5:$Q$24,$J13)) | H13: =IF($A13>$K$2,"",INDEX($R$5:$R$24,$J13)) | I13: =IF($A13>$K$2,"",INDEX($S$5:$S$24,$J13)) | J13: =MATCH(LARGE($T$5:$T$24,A13),$T$5:$T$24,0) -> 4 | L13: ='Product Costing'!A12&"" | M13: ='Product Costing'!AC12 | N13: =IF(L13="","",M13*(1+Default_Retail_Markup)) | O13: =IF(L13="","",M13*(1+Default_Wholesale_Markup)) | P13: =IF(L13="","",N13-M13) | Q13: =IF(L13="","",O13-M13) | R13: =IF(L13="","",IFERROR(P13/N13,0)) | S13: =IF(L13="","",IFERROR(P13/M13,0)) | T13: =IF(L13="",-999999999,P13+(1000-ROW())*0.0000001) -> -999999999
A14: =ROW()-4 -> 10 | B14: =IF($A14>$K$2,"",INDEX($L$5:$L$24,$J14)) | C14: =IF($A14>$K$2,"",INDEX($M$5:$M$24,$J14)) | D14: =IF($A14>$K$2,"",INDEX($N$5:$N$24,$J14)) | E14: =IF($A14>$K$2,"",INDEX($O$5:$O$24,$J14)) | F14: =IF($A14>$K$2,"",INDEX($P$5:$P$24,$J14)) | G14: =IF($A14>$K$2,"",INDEX($Q$5:$Q$24,$J14)) | H14: =IF($A14>$K$2,"",INDEX($R$5:$R$24,$J14)) | I14: =IF($A14>$K$2,"",INDEX($S$5:$S$24,$J14)) | J14: =MATCH(LARGE($T$5:$T$24,A14),$T$5:$T$24,0) -> 4 | L14: ='Product Costing'!A13&"" | M14: ='Product Costing'!AC13 | N14: =IF(L14="","",M14*(1+Default_Retail_Markup)) | O14: =IF(L14="","",M14*(1+Default_Wholesale_Markup)) | P14: =IF(L14="","",N14-M14) | Q14: =IF(L14="","",O14-M14) | R14: =IF(L14="","",IFERROR(P14/N14,0)) | S14: =IF(L14="","",IFERROR(P14/M14,0)) | T14: =IF(L14="",-999999999,P14+(1000-ROW())*0.0000001) -> -999999999
A15: =ROW()-4 -> 11 | B15: =IF($A15>$K$2,"",INDEX($L$5:$L$24,$J15)) | C15: =IF($A15>$K$2,"",INDEX($M$5:$M$24,$J15)) | D15: =IF($A15>$K$2,"",INDEX($N$5:$N$24,$J15)) | E15: =IF($A15>$K$2,"",INDEX($O$5:$O$24,$J15)) | F15: =IF($A15>$K$2,"",INDEX($P$5:$P$24,$J15)) | G15: =IF($A15>$K$2,"",INDEX($Q$5:$Q$24,$J15)) | H15: =IF($A15>$K$2,"",INDEX($R$5:$R$24,$J15)) | I15: =IF($A15>$K$2,"",INDEX($S$5:$S$24,$J15)) | J15: =MATCH(LARGE($T$5:$T$24,A15),$T$5:$T$24,0) -> 4 | L15: ='Product Costing'!A14&"" | M15: ='Product Costing'!AC14 | N15: =IF(L15="","",M15*(1+Default_Retail_Markup)) | O15: =IF(L15="","",M15*(1+Default_Wholesale_Markup)) | P15: =IF(L15="","",N15-M15) | Q15: =IF(L15="","",O15-M15) | R15: =IF(L15="","",IFERROR(P15/N15,0)) | S15: =IF(L15="","",IFERROR(P15/M15,0)) | T15: =IF(L15="",-999999999,P15+(1000-ROW())*0.0000001) -> -999999999
A16: =ROW()-4 -> 12 | B16: =IF($A16>$K$2,"",INDEX($L$5:$L$24,$J16)) | C16: =IF($A16>$K$2,"",INDEX($M$5:$M$24,$J16)) | D16: =IF($A16>$K$2,"",INDEX($N$5:$N$24,$J16)) | E16: =IF($A16>$K$2,"",INDEX($O$5:$O$24,$J16)) | F16: =IF($A16>$K$2,"",INDEX($P$5:$P$24,$J16)) | G16: =IF($A16>$K$2,"",INDEX($Q$5:$Q$24,$J16)) | H16: =IF($A16>$K$2,"",INDEX($R$5:$R$24,$J16)) | I16: =IF($A16>$K$2,"",INDEX($S$5:$S$24,$J16)) | J16: =MATCH(LARGE($T$5:$T$24,A16),$T$5:$T$24,0) -> 4 | L16: ='Product Costing'!A15&"" | M16: ='Product Costing'!AC15 | N16: =IF(L16="","",M16*(1+Default_Retail_Markup)) | O16: =IF(L16="","",M16*(1+Default_Wholesale_Markup)) | P16: =IF(L16="","",N16-M16) | Q16: =IF(L16="","",O16-M16) | R16: =IF(L16="","",IFERROR(P16/N16,0)) | S16: =IF(L16="","",IFERROR(P16/M16,0)) | T16: =IF(L16="",-999999999,P16+(1000-ROW())*0.0000001) -> -999999999
... A24: =ROW()-4 -> 20 | B24: =IF($A24>$K$2,"",INDEX($L$5:$L$24,$J24)) | C24: =IF($A24>$K$2,"",INDEX($M$5:$M$24,$J24)) | D24: =IF($A24>$K$2,"",INDEX($N$5:$N$24,$J24)) | E24: =IF($A24>$K$2,"",INDEX($O$5:$O$24,$J24)) | F24: =IF($A24>$K$2,"",INDEX($P$5:$P$24,$J24)) | G24: =IF($A24>$K$2,"",INDEX($Q$5:$Q$24,$J24)) | H24: =IF($A24>$K$2,"",INDEX($R$5:$R$24,$J24)) | I24: =IF($A24>$K$2,"",INDEX($S$5:$S$24,$J24)) | J24: =MATCH(LARGE($T$5:$T$24,A24),$T$5:$T$24,0) -> 4 | L24: ='Product Costing'!A23&"" | M24: ='Product Costing'!AC23 | N24: =IF(L24="","",M24*(1+Default_Retail_Markup)) | O24: =IF(L24="","",M24*(1+Default_Wholesale_Markup)) | P24: =IF(L24="","",N24-M24) | Q24: =IF(L24="","",O24-M24) | R24: =IF(L24="","",IFERROR(P24/N24,0)) | S24: =IF(L24="","",IFERROR(P24/M24,0)) | T24: =IF(L24="",-999999999,P24+(1000-ROW())*0.0000001) -> -999999999

Sheet Inventory Planning
A1: INVENTORY PLANNING
A2: A simple beginning/purchases/sold tracker for one product at a time.
A4: Select Product: | B4: 10W-40 Motor Oil 1L
A6: INVENTORY
A7: Beginning Inventory (units) | B7: 500
A8: Purchases (units) | B8: 200
A9: Units Sold | B9: 350
A10: Ending Inventory (units) | B10: =B7+B8-B9 -> 350
A11: Cost per Unit (selected product) | B11: =IFERROR(INDEX('Product Costing'!$AC$4:$AC$23,MATCH($B$4,'Product Costing'!$A$4:$A$23,0)),0) -> 21.875 | D11: Auto-filled from Product Costing. You can overwrite it to test a different cost assumption.
A12: Inventory Value | B12: =B10*B11 -> 7656.25
